{
  "media": [
    {
      "id": "1",
      "title": "A Knight's Tale",
      "image": "https://upload.wikimedia.org/wikipedia/en/a/a6/AKnightsTale.jpg",
      "genre": "Action",
      "liked": "Yes",
      "review": "A hugely entertaining medieval romp set to modern rock.",
      "category": "Movies"
    },
    {
      "id": "3",
      "title": "Little Women",
      "image": "https://m.media-amazon.com/images/M/MV5BY2QzYTQyYzItMzAwYi00YjZlLThjNTUtNzMyMDdkYzJiNWM4XkEyXkFqcGdeQXVyMTkxNjUyNQ@@._V1_.jpg",
      "genre": "Romance/Drama",
      "liked": "Yes",
      "review": "The performances by the entire cast are beautiful.",
      "category": "Movies"
    },
    {
      "id": "4",
      "title": "Criminal Minds",
      "image": "https://m.media-amazon.com/images/M/MV5BZWVjZWUyMzUtMGRiMS00MzhkLWI5NTQtYjBmZWVlZThjZjFkXkEyXkFqcGdeQXVyMDA4NzMyOA@@._V1_.jpg",
      "genre": "Drama",
      "liked": "Yes",
      "review": "A psychological thriller that keeps your undivided attention.",
      "category": "TV Shows"
    },
    {
      "id": "5",
      "title": "The Marvelous Mrs. Maisel",
      "image": "https://encrypted-tbn1.gstatic.com/images?q=tbn:ANd9GcQwPPuXpewLvbkWqDA3zYtg5Z1c6O9lg3gvX3G1x6x8Hxfi4BIJ",
      "genre": "Drama",
      "liked": "Yes",
      "review": "The scenes move fast, you won’t find yourself bored at any moment.",
      "category": "TV Shows"
    },
    {
      "id": "6",
      "title": "Gilmore Girls",
      "image": "https://resizing.flixster.com/-XZAfHZM39UwaGJIFWKAE8fS0ak=/v3/t/assets/p7894445_b_v13_ab.jpg",
      "genre": "Drama",
      "liked": "Yes",
      "review": "Gilmore Girls is definitely one of those shows which can dangerously become addictive!",
      "category": "TV Shows"
    },
    {
      "id": "7",
      "title": "11/22/63",
      "image": "https://m.media-amazon.com/images/I/81R-ADdDatL._SY522_.jpg",
      "genre": "Science Fiction",
      "liked": "Yes",
      "review": "The excitement and suspense in this book were astonishing.",
      "category": "Books"
    },
    {
      "id": "44ee",
      "title": "Hearts Beat Loud",
      "image": "https://m.media-amazon.com/images/M/MV5BMjA2MTM2MjcxNV5BMl5BanBnXkFtZTgwMzI3ODgyNTM@._V1_.jpg",
      "genre": "Musical/Comedy",
      "liked": "No",
      "review": "Music is ok but not memorable.",
      "category": "Movies"
    },
    {
      "id": "8feb",
      "title": "Small Great Things",
      "image": "https://m.media-amazon.com/images/I/71BQ5ctKCmL._AC_UF1000,1000_QL80_.jpg",
      "genre": "Realistic Fiction",
      "liked": "Yes",
      "review": "Jodi Picoult can entertain and teach me with her books.",
      "category": "Books"
    },
    {
      "id": "6b4b",
      "title": "The Invisible Life of Addie LaRue",
      "image": "https://images-na.ssl-images-amazon.com/images/S/compressed.photo.goodreads.com/books/1584633432i/50623864.jpg",
      "genre": "Fantasy",
      "liked": "No",
      "review": "There was so much hype about this book, but I don't really get it.",
      "category": "Books"
    }
  ]
}